[
  {
    "id": "access-bars",
    "nameKey": "activity.accessBars"
  },
  {
    "id": "acupunctura",
    "nameKey": "activity.acupunctura"
  },
  {
    "id": "aliniament",
    "nameKey": "activity.aliniament"
  },
  {
    "id": "alte-servicii",
    "nameKey": "activity.alteServicii"
  },
  {
    "id": "aromaterapie",
    "nameKey": "activity.aromaterapie"
  },
  {
    "id": "arta",
    "nameKey": "activity.arta"
  },
  {
    "id": "astrologie",
    "nameKey": "activity.astrologie"
  },
  {
    "id": "ayurveda",
    "nameKey": "activity.ayurveda"
  },
  {
    "id": "biohacking",
    "nameKey": "activity.biohacking"
  },
  {
    "id": "breathwork",
    "nameKey": "activity.breathwork"
  },
  {
    "id": "cheilegenelor",
    "nameKey": "activity.cheileGenelor"
  },
  {
    "id": "chiropractor",
    "nameKey": "activity.chiropractor"
  },
  {
    "id": "coaching",
    "nameKey": "activity.coaching"
  },
  {
    "id": "cupping",
    "nameKey": "activity.cupping"
  },
  {
    "id": "terapie-craniosacrala",
    "nameKey": "activity.terapieCraniosacrala"
  },
  {
    "id": "dans",
    "nameKey": "activity.dans"
  },
  {
    "id": "face-body-paint",
    "nameKey": "activity.faceBodyPaint"
  },
  {
    "id": "fitness",
    "nameKey": "activity.fitness"
  },
  {
    "id": "fizioterapie",
    "nameKey": "activity.fizioterapie"
  },
  {
    "id": "hipnoza",
    "nameKey": "activity.hipnoza"
  },
  {
    "id": "humandesign",
    "nameKey": "activity.humanDesign"
  },
  {
    "id": "humangarage",
    "nameKey": "activity.humanGarage"
  },
  {
    "id": "innerdance",
    "nameKey": "activity.innerdance"
  },
  {
    "id": "kinetoterapie",
    "nameKey": "activity.kinetoterapie"
  },
  {
    "id": "masaj",
    "nameKey": "activity.masaj"
  },
  {
    "id": "medicina-traditionala-chineza",
    "nameKey": "activity.medicinaTraditionala"
  },
  {
    "id": "meditatie-ghidata",
    "nameKey": "activity.meditatieGhidata"
  },
  {
    "id": "miscare-constienta",
    "nameKey": "activity.miscareConstienta"
  },
  {
    "id": "muzica",
    "nameKey": "activity.muzica"
  },
  {
    "id": "neuroptimal",
    "nameKey": "activity.neurOptimal"
  },
  {
    "id": "numerologie",
    "nameKey": "activity.numerologie"
  },
  {
    "id": "nutritie",
    "nameKey": "activity.nutritie"
  },
  {
    "id": "osteopatie",
    "nameKey": "activity.osteopatie"
  },
  {
    "id": "pilates",
    "nameKey": "activity.pilates"
  },
  {
    "id": "psihoterapie",
    "nameKey": "activity.psihoterapie"
  },
  {
    "id": "regresie",
    "nameKey": "activity.regresie"
  },
  {
    "id": "reiki",
    "nameKey": "activity.reiki"
  },
  {
    "id": "scanare-zyto",
    "nameKey": "activity.scanareZyto"
  },
  {
    "id": "sound-healing",
    "nameKey": "activity.soundHealing"
  },
  {
    "id": "tarot",
    "nameKey": "activity.tarot"
  },
  {
    "id": "terapia-bach",
    "nameKey": "activity.terapiaBach"
  },
  {
    "id": "terapia-sphere",
    "nameKey": "activity.terapiaSphere"
  },
  {
    "id": "terapii-shamanice",
    "nameKey": "activity.terapiiShamanice"
  },
  {
    "id": "tetha-healing",
    "nameKey": "activity.tethaHealing"
  },
  {
    "id": "tre",
    "nameKey": "activity.traumaRelease"
  },
  {
    "id": "throat-singing",
    "nameKey": "activity.throatSinging"
  },
  {
    "id": "yoga",
    "nameKey": "activity.yoga"
  },
  {
    "id": "group-actorie",
    "nameKey": "activity.groupActorie"
  },
  {
    "id": "group-alteservicii",
    "nameKey": "activity.groupAlteServicii"
  },
  {
    "id": "group-breathwork",
    "nameKey": "activity.groupBreathwork"
  },
  {
    "id": "group-cheilegenelor",
    "nameKey": "activity.groupCheileGenelor"
  },
  {
    "id": "group-cursuri",
    "nameKey": "activity.groupCursuri"
  },
  {
    "id": "group-dans",
    "nameKey": "activity.groupDans"
  },
  {
    "id": "group-ecstatic-dance",
    "nameKey": "activity.groupEcstaticDance"
  },
  {
    "id": "group-fitness",
    "nameKey": "activity.groupFitness"
  },
  {
    "id": "group-humandesign",
    "nameKey": "activity.groupHumanDesign"
  },
  {
    "id": "group-innerdance",
    "nameKey": "activity.groupInnerdance"
  },
  {
    "id": "group-meditatii-ghidate",
    "nameKey": "activity.groupMeditatiiGhidate"
  },
  {
    "id": "group-miscare-constienta",
    "nameKey": "activity.groupMiscareConstienta"
  },
  {
    "id": "group-muzica",
    "nameKey": "activity.groupMuzica"
  },
  {
    "id": "group-pilates",
    "nameKey": "activity.groupPilates"
  },
  {
    "id": "group-sound-healing",
    "nameKey": "activity.groupSoundHealing"
  },
  {
    "id": "group-tai-chi",
    "nameKey": "activity.groupTaiChi"
  },
  {
    "id": "group-terapie-prin-arta",
    "nameKey": "activity.groupTerapiePrinArta"
  },
  {
    "id": "group-terapii-shamanice",
    "nameKey": "activity.groupTerapiiShamanice"
  },
  {
    "id": "group-throat-singing",
    "nameKey": "activity.groupThroatSinging"
  },
  {
    "id": "group-constelatii-familiale",
    "nameKey": "activity.groupConstelatiiFamiliale"
  },
  {
    "id": "group-qigong",
    "nameKey": "activity.groupQigong"
  },
  {
    "id": "group-workshops",
    "nameKey": "activity.groupWorkshops"
  },
  {
    "id": "group-yoga",
    "nameKey": "activity.groupYoga"
  }
]
